cakelens/__init__.py
cakelens/cli.py
cakelens/constants.py
cakelens/data_types.py
cakelens/datasets.py
cakelens/detect.py
cakelens/model.py
cakelens/utils.py
cakelens_v5-0.1.2.dist-info/licenses/LICENSE
cakelens_v5-0.1.2.dist-info/METADATA
cakelens_v5-0.1.2.dist-info/WHEEL
cakelens_v5-0.1.2.dist-info/entry_points.txt
cakelens_v5-0.1.2.dist-info/top_level.txt
cakelens_v5-0.1.2.dist-info/RECORD
