Metadata-Version: 2.4
Name: cakelens-v5
Version: 0.1.2
Summary: Add your description here
Requires-Python: >=3.11
License-File: LICENSE
Requires-Dist: click>=8.0.0
Requires-Dist: huggingface-hub>=0.33.4
Provides-Extra: torch
Requires-Dist: torch==2.7.0+cu128; extra == "torch"
Requires-Dist: torchvision==0.22.0+cu128; extra == "torch"
Requires-Dist: torchcodec>=0.4.0; extra == "torch"
Dynamic: license-file
